{
  "shoes": [
    {
      "id": "1",
      "name": "Jordan 1 Retro High OG",
      "alias": "Chicago Lost and Found",
      "image": "./images/j1lost.png",
      "price": 380,
      "stock": 8
    },
    {
      "id": "2",
      "name": "Jordan 4 Retro",
      "alias": "Undefeated",
      "image": "./images/undefeated.png",
      "price": 16217,
      "stock": 10
    },
    {
      "id": "3",
      "name": "Nike Air Yeezy 2",
      "alias": "Red October",
      "image": "./images/redoctober.png",
      "price": 9500,
      "stock": 10
    },
    {
      "id": "4",
      "name": "Nike SB Dunk Low",
      "alias": "Freddy Krueger",
      "image": "./images/freddy.png",
      "price": 1500,
      "stock": 10
    },
    {
      "id": "5",
      "name": "Nike SB Dunk Low",
      "alias": "Jarritos",
      "image": "./images/jarritos.png",
      "price": 595,
      "stock": 10
    },
    {
      "id": "6",
      "name": "Nike Kobe Protro",
      "alias": "Reverse Grinch",
      "image": "./images/reversegrinch.png",
      "price": 595,
      "stock": 10
    },
    {
      "id": "7",
      "name": "Jordan 4 Retro",
      "alias": "Manila",
      "image": "./images/manila.png",
      "price": 14500,
      "stock": 10
    },
    {
      "id": "8",
      "name": "adidas Yeezy Boost 350",
      "alias": "Turtledove",
      "image": "./images/turtledove.png",
      "price": 349,
      "stock": 10
    },
    {
      "id": "9",
      "name": "Jordan 1 Retro High",
      "alias": "Dior",
      "image": "./images/dior.png",
      "price": 6556,
      "stock": 10
    },
    {
      "id": "10",
      "name": "Jordan 1 Retro High",
      "alias": "Travis Scott Mocha",
      "image": "./images/tsmochahigh.png",
      "price": 1175,
      "stock": 10
    }
  ],
  "cart": []
}